dm_robotics/geometry/__init__.py
dm_robotics/geometry/geometry.py
dm_robotics/geometry/geometry_test.py
dm_robotics/geometry/joint_angles_distribution.py
dm_robotics/geometry/mujoco_physics.py
dm_robotics/geometry/observation_physics.py
dm_robotics/geometry/observation_physics_test.py
dm_robotics/geometry/pose_distribution.py
dm_robotics/geometry/pose_distribution_test.py
dm_robotics/geometry/jax_geometry/__init__.py
dm_robotics/geometry/jax_geometry/auto_vectorize.py
dm_robotics/geometry/jax_geometry/auto_vectorize_test.py
dm_robotics/geometry/jax_geometry/basic_types.py
dm_robotics/geometry/jax_geometry/camera.py
dm_robotics/geometry/jax_geometry/camera_test.py
dm_robotics/geometry/jax_geometry/frame_geometry.py
dm_robotics/geometry/jax_geometry/frame_geometry_test.py
dm_robotics/geometry/jax_geometry/geometry_utils.py
dm_robotics/geometry/jax_geometry/geometry_utils_test.py
dm_robotics/geometry/jax_geometry/normal_geometry.py
dm_robotics/geometry/jax_geometry/normal_geometry_test.py
dm_robotics/geometry/jax_geometry/pointcloud_stamped.py
dm_robotics/geometry/jax_geometry/pointcloud_stamped_test.py
dm_robotics/geometry/jax_geometry/projective_geometry.py
dm_robotics/geometry/jax_geometry/projective_geometry_test.py
dm_robotics/geometry/jax_geometry/_impl/map_coordinates.py
dm_robotics/geometry/jax_geometry/_impl/map_coordinates_test.py
dm_robotics_geometry-0.10.0.dist-info/METADATA
dm_robotics_geometry-0.10.0.dist-info/WHEEL
dm_robotics_geometry-0.10.0.dist-info/top_level.txt
dm_robotics_geometry-0.10.0.dist-info/zip-safe
dm_robotics_geometry-0.10.0.dist-info/RECORD
