Metadata-Version: 2.4
Name: dm_robotics-geometry
Version: 0.10.0
Summary: This library provides primitives for dealing with scene and robot geometry
Home-page: https://github.com/deepmind/dm_robotics/tree/main/py/geometry
Author: DeepMind
License: Apache 2.0
Classifier: Development Status :: 5 - Production/Stable
Classifier: Programming Language :: Python :: 3
Classifier: License :: OSI Approved :: Apache Software License
Classifier: Operating System :: OS Independent
Classifier: Topic :: Software Development :: Libraries
Classifier: Topic :: Scientific/Engineering
Classifier: Topic :: Scientific/Engineering :: Mathematics
Requires-Python: >=3.9, <3.13
Requires-Dist: dm_robotics-transformations
Requires-Dist: numpy<3.0,>=2.0
Requires-Dist: dm_control==1.0.31
Requires-Dist: mujoco==3.3.3
Requires-Dist: six>=1.16.0
Requires-Dist: chex>=0.1.84
Dynamic: author
Dynamic: classifier
Dynamic: description
Dynamic: description-content-type
Dynamic: home-page
Dynamic: license
Dynamic: requires-dist
Dynamic: requires-python
Dynamic: summary
